CgdbZhongwenShouce/README.md
CgdbZhongwenShouce/__init__.py
CgdbZhongwenShouce/__main__.py
CgdbZhongwenShouce/file.epub
CgdbZhongwenShouce/index.html
CgdbZhongwenShouce/css/__init__.py
CgdbZhongwenShouce/css/annotations.css
CgdbZhongwenShouce/css/main.css
CgdbZhongwenShouce/css/normalize.css
CgdbZhongwenShouce/css/popup.css
CgdbZhongwenShouce/font/__init__.py
CgdbZhongwenShouce/font/fontello.eot
CgdbZhongwenShouce/font/fontello.svg
CgdbZhongwenShouce/font/fontello.ttf
CgdbZhongwenShouce/font/fontello.woff
CgdbZhongwenShouce/img/__init__.py
CgdbZhongwenShouce/img/annotator-glyph-sprite.png
CgdbZhongwenShouce/img/annotator-icon-sprite.png
CgdbZhongwenShouce/img/apple-touch-icon.png
CgdbZhongwenShouce/img/cancelfullscreen.png
CgdbZhongwenShouce/img/close.png
CgdbZhongwenShouce/img/fullscreen.png
CgdbZhongwenShouce/img/loader.gif
CgdbZhongwenShouce/img/menu-icon.png
CgdbZhongwenShouce/img/save.png
CgdbZhongwenShouce/img/saved.png
CgdbZhongwenShouce/img/settings-s.png
CgdbZhongwenShouce/img/settings.png
CgdbZhongwenShouce/img/star.png
CgdbZhongwenShouce/js/__init__.py
CgdbZhongwenShouce/js/epub.js
CgdbZhongwenShouce/js/epub.min.js
CgdbZhongwenShouce/js/epub.min.map
CgdbZhongwenShouce/js/hooks.min.js
CgdbZhongwenShouce/js/hooks.min.map
CgdbZhongwenShouce/js/reader.js
CgdbZhongwenShouce/js/reader.js.map
CgdbZhongwenShouce/js/reader.min.js
CgdbZhongwenShouce/js/reader.min.map
CgdbZhongwenShouce/js/hooks/__init__.py
CgdbZhongwenShouce/js/hooks/extensions/__init__.py
CgdbZhongwenShouce/js/hooks/extensions/highlight.js
CgdbZhongwenShouce/js/libs/__init__.py
CgdbZhongwenShouce/js/libs/jquery.min.js
CgdbZhongwenShouce/js/libs/localforage.min.js
CgdbZhongwenShouce/js/libs/screenfull.js
CgdbZhongwenShouce/js/libs/screenfull.min.js
CgdbZhongwenShouce/js/libs/zip.min.js
CgdbZhongwenShouce/js/plugins/__init__.py
CgdbZhongwenShouce/js/plugins/hypothesis.js
CgdbZhongwenShouce/js/plugins/search.js
cgdb_zhongwen_shouce-2024.3.1.0.dist-info/METADATA
cgdb_zhongwen_shouce-2024.3.1.0.dist-info/WHEEL
cgdb_zhongwen_shouce-2024.3.1.0.dist-info/entry_points.txt
cgdb_zhongwen_shouce-2024.3.1.0.dist-info/top_level.txt
cgdb_zhongwen_shouce-2024.3.1.0.dist-info/RECORD
